README.rst
setup.py
dask_adlfs/__init__.py
dask_adlfs/core.py
dask_adlfs.egg-info/PKG-INFO
dask_adlfs.egg-info/SOURCES.txt
dask_adlfs.egg-info/dependency_links.txt
dask_adlfs.egg-info/not-zip-safe
dask_adlfs.egg-info/pbr.json
dask_adlfs.egg-info/requires.txt
dask_adlfs.egg-info/top_level.txt