Metadata-Version: 1.2
Name: dask-adlfs
Version: 0.0.1
Summary: Access Azure Datalake Storage from Dask
Home-page: https://github.com/dask/dask-adlfs/
Maintainer: Martin Durant
Maintainer-email: martin.durant@utoronto.ca
License: BSD
Keywords: file-system,dask,azure
Platform: UNKNOWN
